pyFortiManagerAPI.py
pyFortiManagerAPI-0.2.2.dist-info/LICENSE.txt
pyFortiManagerAPI-0.2.2.dist-info/METADATA
pyFortiManagerAPI-0.2.2.dist-info/WHEEL
pyFortiManagerAPI-0.2.2.dist-info/top_level.txt
pyFortiManagerAPI-0.2.2.dist-info/RECORD
