Metadata-Version: 2.1
Name: pyFortiManagerAPI
Version: 0.2.2
Summary: A Python wrapper for the FortiManager REST API
Home-page: https://github.com/akshaymane920/pyFortiManagerAPI
Author: Akshay Mane
Author-email: akshaymane920@gmail.com
Keywords: FortiManager,RestAPI,API,FortiGate,Fortinet,python,FortiManager API,FortiManager API Python,Python examples
Classifier: License :: OSI Approved :: MIT License
Classifier: Programming Language :: Python :: 3.6
Classifier: Programming Language :: Python :: 3.7
Classifier: Programming Language :: Python :: 3.8
Classifier: Programming Language :: Python :: 3.9
Classifier: Programming Language :: Python :: 3.10
Classifier: Operating System :: OS Independent
License-File: LICENSE.txt
Requires-Dist: requests
Requires-Dist: urllib3
